LICENSE
README.md
setup.py
hockey_rink/__init__.py
hockey_rink/_base_rink.py
hockey_rink/_rink_plot.py
hockey_rink/plotting.py
hockey_rink/rink.py
hockey_rink/rink_feature.py
hockey_rink.egg-info/PKG-INFO
hockey_rink.egg-info/SOURCES.txt
hockey_rink.egg-info/dependency_links.txt
hockey_rink.egg-info/not-zip-safe
hockey_rink.egg-info/requires.txt
hockey_rink.egg-info/top_level.txt