Metadata-Version: 2.1
Name: hockey_rink
Version: 1.1.4
Summary: A Python library for plotting hockey rinks with Matplotlib.
Home-page: https://github.com/the-bucketless/hockey_rink
Author: The Bucketless
Author-email: thebucketless@protonmail.com
License: GNU General Public License v3 (GPLv3)
Classifier: Development Status :: 3 - Alpha
Classifier: Framework :: Matplotlib
Classifier: License :: OSI Approved :: GNU General Public License v3 (GPLv3)
Classifier: Programming Language :: Python :: 3.6
License-File: LICENSE
Requires-Dist: matplotlib
Requires-Dist: numpy
Requires-Dist: pillow
